youtube_upload_monetization/__init__.py
youtube_upload_monetization/const.py
youtube_upload_monetization-1.4.dist-info/LICENSE
youtube_upload_monetization-1.4.dist-info/METADATA
youtube_upload_monetization-1.4.dist-info/WHEEL
youtube_upload_monetization-1.4.dist-info/top_level.txt
youtube_upload_monetization-1.4.dist-info/RECORD
