Metadata-Version: 2.1
Name: youtube-upload-monetization
Version: 1.4
Summary: Uploads videos to youtube through the use of selenium
Home-page: UNKNOWN
Author: Chance Vodnoy
Author-email: chancevodnoy129@gmail.com
License: UNKNOWN
Platform: UNKNOWN
